corlace/__init__.py
corlace/sdk.py
corlace_sdk-0.1.0.dist-info/LICENSE
corlace_sdk-0.1.0.dist-info/METADATA
corlace_sdk-0.1.0.dist-info/WHEEL
corlace_sdk-0.1.0.dist-info/top_level.txt
corlace_sdk-0.1.0.dist-info/RECORD
